[{"Website":"http://www.newbelgium.com/%20tour-de-fat","Start":"07/29/2017","End":"07/29/2017","Event":"Tour de Fat Chicago","Location":"USA-IL","Type":"Other"},{"Website":"http://www.newbelgium.com/%20tour-de-fat","Start":"07/29/2017","End":"07/29/2017","Event":"Tour de Fat Grand Rapids","Location":"USA-MI","Type":"Other"},{"Website":"http://www.newbelgium.com/%20tour-de-fat","Start":"08/05/2017","End":"08/05/2017","Event":"Tour de Fat Indianapolis","Location":"USA-IN","Type":"Other"},{"Website":"http://www.newbelgium.com/%20tour-de-fat","Start":"08/12/2017","End":"08/12/2017","Event":"Tour de Fat Detroit","Location":"USA-MI","Type":"Other"},{"Website":"http://www.newbelgium.com/%20tour-de-fat","Start":"08/12/2017","End":"08/12/2017","Event":"Tour de Fat Boise","Location":"USA-ID","Type":"Other"},{"Website":"http://www.newbelgium.com/%20tour-de-fat","Start":"08/12/2017","End":"08/12/2017","Event":"Tour de Fat Kansas City","Location":"USA-KS","Type":"Other"},{"Website":"http://www.newbelgium.com/%20tour-de-fat","Start":"08/19/2017","End":"08/19/2017","Event":"Tour de Fat Minneapolis","Location":"USA-MN","Type":"Other"},{"Website":"http://www.newbelgium.com/%20tour-de-fat","Start":"08/19/2017","End":"08/19/2017","Event":"Tour de Fat San Francisco","Location":"USA-CA","Type":"Other"},{"Website":"http://sundaystreetssf.com/","Start":"08/20/2017","End":"08/20/2017","Event":"SF Sunday Streets - Tenderloin","Location":"USA-CA","Type":"Other"},{"Website":"http://www.newbelgium.com/%20tour-de-fat","Start":"08/23/2017","End":"08/23/2017","Event":"Tour de Fat Madison","Location":"USA-WI","Type":"Other"},{"Website":"http://www.newbelgium.com/%20tour-de-fat","Start":"08/25/2017","End":"08/25/2017","Event":"Tour de Fat Boulder","Location":"USA-CO","Type":"Other"},{"Website":"http://www.newbelgium.com/%20tour-de-fat","Start":"08/26/2017","End":"08/26/2017","Event":"Tour de Fat Denver","Location":"USA-CO","Type":"Other"},{"Website":"http://www.newbelgium.com/%20tour-de-fat","Start":"08/26/2017","End":"08/26/2017","Event":"Tour de Fat Colorado Springs","Location":"USA-CO","Type":"Other"},{"Website":"http://www.newbelgium.com/%20tour-de-fat","Start":"09/02/2017","End":"09/02/2017","Event":"Tour de Fat Fort Collins","Location":"USA-CO","Type":"Other"},{"Website":"http://sundaystreetssf.com/","Start":"09/10/2017","End":"09/10/2017","Event":"SF Sunday Streets - Western Addition","Location":"USA-CA","Type":"Other"},{"Website":"http://sundaystreetssf.com/","Start":"10/01/2017","End":"10/01/2017","Event":"SF Sunday Streets - Excelsior","Location":"USA-CA","Type":"Other"},{"Website":"http://www.newbelgium.com/%20tour-de-fat","Start":"10/07/2017","End":"10/07/2017","Event":"Tour de Fat Tempe","Location":"USA-AZ","Type":"Other"}]